faas_grip.py
setup.cfg
setup.py
faas_grip.egg-info/PKG-INFO
faas_grip.egg-info/SOURCES.txt
faas_grip.egg-info/dependency_links.txt
faas_grip.egg-info/requires.txt
faas_grip.egg-info/top_level.txt