Metadata-Version: 1.1
Name: faas-grip
Version: 1.0.1
Summary: FaaS GRIP library
Home-page: https://github.com/fanout/python-faas-grip
Author: Justin Karneges
Author-email: justin@fanout.io
License: MIT
Platform: UNKNOWN
Classifier: Topic :: Utilities
Classifier: License :: OSI Approved :: MIT License
